staticsql/__init__.py
staticsql/api.py
staticsql/database.py
staticsql/entity.py
staticsql/sql.py
staticsql/util.py
tests/__init__.py
tests/test_complex_sql.py
tests/test_json.py
tests/test_simple_sql.py
staticsql-0.9.4.dist-info/LICENCE
staticsql-0.9.4.dist-info/METADATA
staticsql-0.9.4.dist-info/WHEEL
staticsql-0.9.4.dist-info/top_level.txt
staticsql-0.9.4.dist-info/RECORD
