Metadata-Version: 2.1
Name: staticsql
Version: 0.9.4
Summary: Library for working with StaticSQL entity metadata files.
Home-page: https://github.com/iteg-hq/staticsql
Author: Frederik Siegumfeldt
Author-email: siegumfeldt@gmail.com
License: UNKNOWN
Platform: UNKNOWN
Classifier: Programming Language :: Python :: 3
Classifier: License :: OSI Approved :: MIT License
Classifier: Operating System :: OS Independent
Requires-Python: >=3.6
